decision_tree_kv/__init__.py
decision_tree_kv-0.0.2.dist-info/LICENSE
decision_tree_kv-0.0.2.dist-info/METADATA
decision_tree_kv-0.0.2.dist-info/WHEEL
decision_tree_kv-0.0.2.dist-info/top_level.txt
decision_tree_kv-0.0.2.dist-info/RECORD
