Metadata-Version: 2.1
Name: decision-tree-kv
Version: 0.0.2
Summary: CART decision tree
Home-page: https://github.com/kopylovvlad/decision_tree_kv
Author: Vladislav Kopylov
Author-email: kopylov.vlad@gmail.com
License: UNKNOWN
Platform: UNKNOWN
Requires-Python: >=3.5
